abstract_logger/__init__.py
abstract_logger/anonymizer.py
abstract_logger/config_loader.py
abstract_logger/logger.py
abstract_logger/test.py
log_abstractor-1.1.19.dist-info/METADATA
log_abstractor-1.1.19.dist-info/WHEEL
log_abstractor-1.1.19.dist-info/top_level.txt
log_abstractor-1.1.19.dist-info/RECORD
